ticketref/__init__.py
ticketref/api.py
ticketref/model.py
ticketref/utils.py
ticketref/web_ui.py
ticketref/htdocs/ticket.css
ticketref/htdocs/ticket.js
ticketref/locale/messages.pot
ticketref/locale/ja/LC_MESSAGES/ticketref.mo
ticketref/locale/ja/LC_MESSAGES/ticketref.po
TracTicketReferencePlugin-0.5.2.dist-info/LICENSE
TracTicketReferencePlugin-0.5.2.dist-info/METADATA
TracTicketReferencePlugin-0.5.2.dist-info/WHEEL
TracTicketReferencePlugin-0.5.2.dist-info/entry_points.txt
TracTicketReferencePlugin-0.5.2.dist-info/top_level.txt
TracTicketReferencePlugin-0.5.2.dist-info/RECORD
