Metadata-Version: 2.1
Name: TracTicketReferencePlugin
Version: 0.5.2
Summary: Provides support for ticket cross reference for Trac
Home-page: https://trac-hacks.org/wiki/TracTicketReferencePlugin
Author: Tetsuya Morimoto
Author-email: tetsuya.morimoto@gmail.com
License: Apache License 2.0
Keywords: trac,plugin,ticket,cross-reference
Classifier: Framework :: Trac
Classifier: Development Status :: 4 - Beta
Classifier: Environment :: Web Environment
Classifier: License :: OSI Approved :: Apache Software License
Classifier: Intended Audience :: Developers
Classifier: Operating System :: OS Independent
Classifier: Programming Language :: Python :: 2.7
Classifier: Programming Language :: Python :: 3
Classifier: Topic :: Software Development
License-File: LICENSE
Requires-Dist: Trac >=0.12
